phenograph/__init__.py
phenograph/bruteforce_nn.py
phenograph/classify.py
phenograph/cluster.py
phenograph/core.py
phenograph/version.py
phenograph/louvain/community
phenograph/louvain/community.exe
phenograph/louvain/convert
phenograph/louvain/convert.exe
phenograph/louvain/hierarchy
phenograph/louvain/hierarchy.exe
phenograph/louvain/linux-community
phenograph/louvain/linux-convert
phenograph/louvain/linux-hierarchy
phenograph/louvain/louvain-readme.txt
phenograph/louvain/phenograph-readme.txt
tests/__init__.py
tests/conftest.py
tests/test_classify.py
tests/test_cluster.py
tests/test_core.py
PhenoGraph-1.5.7.dist-info/LICENSE
PhenoGraph-1.5.7.dist-info/METADATA
PhenoGraph-1.5.7.dist-info/WHEEL
PhenoGraph-1.5.7.dist-info/top_level.txt
PhenoGraph-1.5.7.dist-info/RECORD
