Metadata-Version: 2.1
Name: PhenoGraph
Version: 1.5.7
Summary: Graph-based clustering for high-dimensional single-cell data
Home-page: https://github.com/dpeerlab/PhenoGraph.git
Author: Jacob Levine
Author-email: jl3545@columbia.edu
License: LICENSE
Platform: UNKNOWN
Classifier: Programming Language :: Python :: 3
Classifier: License :: OSI Approved :: MIT License
Classifier: Operating System :: OS Independent
Classifier: Operating System :: POSIX :: Linux
Classifier: Development Status :: 5 - Production/Stable
Classifier: Topic :: Scientific/Engineering :: Bio-Informatics
Classifier: Topic :: Scientific/Engineering :: Visualization
Requires-Python: >=3.6
Requires-Dist: leidenalg (>=0.8.2)
Requires-Dist: setuptools (>=18.0.1)
Requires-Dist: numpy (>=1.12)
Requires-Dist: scipy (>=1.5.1)
Requires-Dist: scikit-learn (>=0.17)
Requires-Dist: psutil (>4)
